cubbi/__init__.py
cubbi/__main__.py
cubbi/cli.py
cubbi/config.py
cubbi/configure.py
cubbi/container.py
cubbi/cubbi_inspector_entrypoint.sh
cubbi/mcp.py
cubbi/model_fetcher.py
cubbi/models.py
cubbi/session.py
cubbi/user_config.py
cubbi/images/base.py
cubbi/images/cubbi_init.py
cubbi/images/init-status.sh
cubbi/images/aider/Dockerfile
cubbi/images/aider/README.md
cubbi/images/aider/aider_plugin.py
cubbi/images/aider/cubbi_image.yaml
cubbi/images/aider/test_aider.py
cubbi/images/claudecode/Dockerfile
cubbi/images/claudecode/README.md
cubbi/images/claudecode/claudecode_plugin.py
cubbi/images/claudecode/cubbi_image.yaml
cubbi/images/claudecode/test_claudecode.py
cubbi/images/crush/Dockerfile
cubbi/images/crush/README.md
cubbi/images/crush/crush_plugin.py
cubbi/images/crush/cubbi_image.yaml
cubbi/images/goose/Dockerfile
cubbi/images/goose/README.md
cubbi/images/goose/cubbi_image.yaml
cubbi/images/goose/goose_plugin.py
cubbi/images/opencode/Dockerfile
cubbi/images/opencode/README.md
cubbi/images/opencode/cubbi_image.yaml
cubbi/images/opencode/opencode_plugin.py
cubbi/utils/git.py
cubbi-0.5.0.dist-info/METADATA
cubbi-0.5.0.dist-info/WHEEL
cubbi-0.5.0.dist-info/entry_points.txt
cubbi-0.5.0.dist-info/licenses/LICENSE
cubbi-0.5.0.dist-info/RECORD
